lvmecp/__init__.py
lvmecp/__main__.py
lvmecp/dome.py
lvmecp/exceptions.py
lvmecp/hvac.py
lvmecp/lights.py
lvmecp/maskbits.py
lvmecp/modbus.py
lvmecp/module.py
lvmecp/plc.py
lvmecp/safety.py
lvmecp/simulator.py
lvmecp/tools.py
lvmecp/actor/__init__.py
lvmecp/actor/actor.py
lvmecp/actor/commands/__init__.py
lvmecp/actor/commands/dome.py
lvmecp/actor/commands/e_stop.py
lvmecp/actor/commands/engineering.py
lvmecp/actor/commands/heartbeat.py
lvmecp/actor/commands/lights.py
lvmecp/actor/commands/modbus.py
lvmecp/actor/commands/status.py
lvmecp/etc/lvmecp.yml
lvmecp/etc/schema.json
sdss_lvmecp-1.3.3.dist-info/METADATA
sdss_lvmecp-1.3.3.dist-info/WHEEL
sdss_lvmecp-1.3.3.dist-info/entry_points.txt
sdss_lvmecp-1.3.3.dist-info/licenses/LICENSE.md
sdss_lvmecp-1.3.3.dist-info/RECORD
