Metadata-Version: 2.4
Name: sdss-lvmecp
Version: 1.3.3
Summary: A library and actor to communicate with an SDSS-V LVM Enclosure
Project-URL: Homepage, https://github.com/sdss/lvmecp
Project-URL: Repository, https://github.com/sdss/lvmecp
Project-URL: Documentation, https://sdss-lvmecp.readthedocs.org
Author-email: José Sánchez-Gallego <gallegoj@uw.edu>, mingyeong yang <mingyeong@khu.ac.kr>
License: BSD-3-Clause
License-File: LICENSE.md
Requires-Python: <4,>=3.11
Requires-Dist: click-default-group>=1.2.2
Requires-Dist: lvmopstools[ephemeris,slack]>=0.5.14
Requires-Dist: pymodbus<3.7,>=3.6.0
Requires-Dist: pyserial-asyncio>=0.6
Requires-Dist: redis[hiredis]>=5.2.1
Requires-Dist: sdss-clu>=2.4.3
Requires-Dist: sdsstools>=1.9.1
